mirror_up/__init__.py
mirror_up/__main__.py
mirror_up/_utils.py
mirror_up/mirror_ace.py
mirror_up/mirror_ace_cli.py
mirror_up-0.1.6.dist-info/LICENSE
mirror_up-0.1.6.dist-info/WHEEL
mirror_up-0.1.6.dist-info/METADATA
mirror_up-0.1.6.dist-info/RECORD
