Metadata-Version: 2.1
Name: mirror-up
Version: 0.1.6
Summary: Upload files to online mirroring services.
Home-page: https://github.com/mycsina/mirror_up
License: MIT
Author: Mycsina
Author-email: mycsina@protonmail.com
Requires-Python: >=3.9,<4.0
Classifier: Development Status :: 3 - Alpha
Classifier: Intended Audience :: End Users/Desktop
Classifier: License :: OSI Approved :: MIT License
Classifier: Natural Language :: English
Classifier: Programming Language :: Python :: 3
Classifier: Programming Language :: Python :: 3.10
Classifier: Programming Language :: Python :: 3.9
Requires-Dist: alive-progress (>=2.3.1,<3.0.0)
Requires-Dist: format-byte (>=1.1.1,<2.0.0)
Requires-Dist: httpx (==0.23.0)
Requires-Dist: multivolumefile (>=0.2.3,<0.3.0)
Requires-Dist: notify-py (>=0.3.3,<0.4.0)
Requires-Dist: pyperclip (>=1.8.2,<2.0.0)
Requires-Dist: python-dotenv (==0.20.0)
Requires-Dist: trio (>=0.20.0,<0.21.0)
Requires-Dist: typer (>=0.4.0,<0.5.0)
